blobfish/__init__.py
blobfish/main.py
blobfish-0.1.1.dist-info/METADATA
blobfish-0.1.1.dist-info/WHEEL
blobfish-0.1.1.dist-info/top_level.txt
blobfish-0.1.1.dist-info/RECORD
