Metadata-Version: 2.1
Name: blobfish
Version: 0.1.1
Summary: BLOBFISH!
Author: ilpy
Author-email: <ilpy@proton.me>
